gli4py/__init__.py
gli4py/enums.py
gli4py/error_codes.py
gli4py/error_handling.py
gli4py/glinet.py
gli4py-0.0.15.dist-info/METADATA
gli4py-0.0.15.dist-info/WHEEL
gli4py-0.0.15.dist-info/licenses/LICENSE
gli4py-0.0.15.dist-info/RECORD
