Metadata-Version: 2.4
Name: gli4py
Version: 0.0.15
Summary: A python 3 API wrapper for GL-inet routers for consumption by Home Assistant
License: GNU GENERAL PUBLIC LICENSE
License-File: LICENSE
Author: HarvsG
Author-email: doctor@codingdoctor.co.uk
Requires-Python: >=3.11,<4.0
Classifier: License :: Other/Proprietary License
Classifier: Programming Language :: Python :: 3
Classifier: Programming Language :: Python :: 3.11
Classifier: Programming Language :: Python :: 3.12
Classifier: Programming Language :: Python :: 3.13
Classifier: Programming Language :: Python :: 3.14
Requires-Dist: passlib (>=1.7.4,<2.0.0)
Requires-Dist: semver (>=3.0.0,<4.0.0)
Requires-Dist: uplink (==0.10.0)
